[
  {
    "id": 0,
    "name": "Yi Sang",
    "icon": "Yi_Sang_Icon.png",
    "identities": 
    [
      {
        "name": "[LCB Sinner] Yi Sang",
        "rarity": 0,
        "damageTypes": ["Slash", "Pierce"],
        "sinTypes": ["Gloom", "Envy", "Sloth"],
        "image":"yi_sang/lcb_sinner/lcb_sinner.png"
      },
      {
        "name": "[Seven Assoc. South Section 6] Yi Sang",
        "rarity": 1,
        "damageTypes": ["Pierce", "Blunt"],
        "sinTypes": ["Gloom", "Sloth", "Gluttony"],
        "image":"yi_sang/seven_assoc_south_section_6/seven_assoc_south_section_6.png"
      },
      {
        "name": "[Molar Office] Yi Sang",
        "rarity": 1,
        "damageTypes": ["Pierce", "Blunt"],
        "sinTypes": ["Lust", "Sloth", "Wrath"],
        "image":"yi_sang/molar_office_fixer/molar_office_fixer.png"
      },
      {
        "name": "[The Pequod First Mate] Yi Sang",
        "rarity": 1,
        "damageTypes": ["Pierce"],
        "sinTypes": ["Pride", "Envy", "Gluttony"],
        "image":"yi_sang/the_pequod_first_mate/the_pequod_first_mate.png"
      },
      {
        "name": "[Dieci Assoc. South Section 4] Yi Sang",
        "rarity": 1,
        "damageTypes": ["Pierce", "Blunt"],
        "sinTypes": ["Sloth", "Lust", "Gluttony"],
        "image":"yi_sang/dieci_assoc_south_section_4/dieci_assoc_south_section_4.png"
      },
      {
        "name": "[LCE E.G.O::Lantern] Yi Sang",
        "rarity": 1,
        "damageTypes": ["Pierce", "Blunt"],
        "sinTypes": ["Sloth", "Wrath", "Gluttony"],
        "image":"yi_sang/lce_ego_lantern/lce_ego_lantern.png"
      },
      {
        "name": "[Blade Lineage Salsu] Yi Sang",
        "rarity": 2,
        "damageTypes": ["Slash"],
        "sinTypes": ["Wrath", "Envy", "Pride"],
        "image":"yi_sang/blade_lineage_salsu/blade_lineage_salsu.png"
      },
      {
        "name": "[Effloresced E.G.O::Spicebush] Yi Sang",
        "rarity": 2,
        "damageTypes": ["Pierce", "Blunt"],
        "sinTypes": ["Gluttony", "Sloth", "Pride"],
        "image":"yi_sang/effloresced_ego_spicebush/effloresced_ego_spicebush.png"
      },
      {
        "name": "[W Corp. L3 Cleanup Agent] Yi Sang",
        "rarity": 2,
        "damageTypes": ["Slash", "Pierce"],
        "sinTypes": ["Sloth", "Gloom", "Gluttony"],
        "image":"yi_sang/w_corp_l3_cleanup_agent/w_corp_l3_cleanup_agent.png"
      },
      {
        "name": "[The Ring Pointillist Student] Yi Sang",
        "rarity": 2,
        "damageTypes": ["Pierce"],
        "sinTypes": ["Sloth", "Lust", "Gloom"],
        "image":"yi_sang/the_ring_pointillist_student/the_ring_pointillist_student.png"
      },
      {
        "name": "[Lobotomy E.G.O::Solemn Lament] Yi Sang",
        "rarity": 2,
        "damageTypes": ["Pierce"],
        "sinTypes": ["Sloth", "Pride", "Gloom"],
        "image":"yi_sang/lobotomy_ego_solemn_lament/lobotomy_ego_solemn_lament.png"
      },
      {
        "name": "[Liu Assoc. South Section 3] Yi Sang",
        "rarity": 2,
        "damageTypes": ["Slash"],
        "sinTypes": ["Sloth", "Envy", "Wrath"],
        "image":"yi_sang/liu_assoc_south_section_3/liu_assoc_south_section_3.png"
      },
      {
        "name": "[N Corp. E.G.O::Fell Bullet] Yi Sang",
        "rarity": 2,
        "damageTypes": ["Blunt", "Pierce"],
        "sinTypes": ["Wrath", "Lust", "Pride"],
        "image":"yi_sang/n_corp_ego_fell_bullet/n_corp_ego_fell_bullet.png"
      }
    ]
  },
  {
    "id": 1,
    "name": "Faust",
    "icon": "Faust_Icon.png",
    "identities": 
    [
      {
        "name": "[LCB Sinner] Faust",
        "rarity": 0,
        "damageTypes": ["Blunt", "Pierce"],
        "sinTypes": ["Pride", "Gluttony", "Sloth"],
        "image":"faust/lcb_sinner/lcb_sinner.png"
      },
      {
        "name": "[W Corp. L2 Cleanup Agent] Faust",
        "rarity": 1,
        "damageTypes": ["Blunt"],
        "sinTypes": ["Envy", "Gloom", "Wrath"],
        "image":"faust/w_corp_l2_cleanup_agent/w_corp_l2_cleanup_agent.png"
      },
      {
        "name": "[Lobotomy Corp. Remnant] Faust",
        "rarity": 1,
        "damageTypes": ["Slash", "Pierce"],
        "sinTypes": ["Lust", "Gloom", "Envy"],
        "image":"faust/lobotomy_corp_remnant/lobotomy_corp_remnant.png"
      },
      {
        "name": "[Zwei Assoc. South Section 4] Faust",
        "rarity": 1,
        "damageTypes": ["Slash", "Pierce"],
        "sinTypes": ["Lust", "Gloom", "Envy"],
        "image":"faust/zwei_assoc_south_section_4/zwei_assoc_south_section_4.png"
      },
      {
        "name": "[Wuthering Heights Butler] Faust",
        "rarity": 1,
        "damageTypes": ["Slash", "Blunt"],
        "sinTypes": ["Wrath", "Gloom", "Lust"],
        "image":"faust/wuthering_heights_butler/wuthering_heights_butler.png"
      },
      {
        "name": "[The One Who Grips] Faust",
        "rarity": 2,
        "damageTypes": ["Pierce", "Blunt"],
        "sinTypes": ["Envy", "Lust", "Pride"],
        "image":"faust/the_one_who_grips/the_one_who_grips.png"
      },
      {
        "name": "[Seven Assoc. South Section 4] Faust",
        "rarity": 2,
        "damageTypes": ["Slash", "Slash"],
        "sinTypes": ["Envy", "Gloom", "Gluttony", "Lust"],
        "image":"faust/seven_assoc_south_section_4/seven_assoc_south_section_4.png"
      },
      {
        "name": "[Lobotomy E.G.O::Regret] Faust",
        "rarity": 2,
        "damageTypes": ["Blunt"],
        "sinTypes": ["Sloth", "Pride", "Lust"],
        "image":"faust/lobotomy_ego_regret/lobotomy_ego_regret.png"
      },
      {
        "name": "[Blade Lineage Salsu] Faust",
        "rarity": 2,
        "damageTypes": ["Slash", "Pierce"],
        "sinTypes": ["Sloth", "Pride", "Gloom"],
        "image":"faust/blade_lineage_salsu/blade_lineage_salsu.png"
      },
      {
        "name": "[MultiCrack Office Rep] Faust",
        "rarity": 2,
        "damageTypes": ["Slash", "Blunt"],
        "sinTypes": ["Envy", "Gloom", "Gloom"],
        "image":"faust/multicrack_office_rep/multicrack_office_rep.png"
      },
      {
        "name": "[LCE E.G.O::Ardor Blossom Star] Faust",
        "rarity": 2,
        "damageTypes": ["Blunt"],
        "sinTypes": ["Wrath", "Pride", "Sloth"],
        "image":"faust/lce_ego_ardor_blossom_star/lce_ego_ardor_blossom_star.png"
      },
      {
        "name": "[Heishou Pack - Mao Branch Adept] Faust",
        "rarity": 2,
        "damageTypes": ["Slash"],
        "sinTypes": ["Gluttony", "Pride", "Sloth"],
        "image":"faust/heishou_pack_mao_branch_adept/heishou_pack_mao_branch_adept.png"
      }
    ]
  },
  {
    "id": 2,
    "name": "Don Quixote",
    "icon": "Don_Quixote_Icon.png",
    "identities": 
    [
      {
        "name": "[LCB Sinner] Don Quixote",
        "rarity": 0,
        "damageTypes": ["Pierce"],
        "sinTypes": ["Lust", "Envy", "Gluttony"],
        "image":"don_quixote/lcb_sinner/lcb_sinner.png"
      },
      {
        "name": "[Shi Assoc. South Section 5 Director] Don Quixote",
        "rarity": 1,
        "damageTypes": ["Slash"],
        "sinTypes": ["Wrath", "Envy", "Lust"],
        "image":"don_quixote/shi_assoc_south_section_5_director/shi_assoc_south_section_5_director.png"
      },
      {
        "name": "[N Corp. Mittelhammer] Don Quixote",
        "rarity": 1,
        "damageTypes": ["Pierce", "Blunt"],
        "sinTypes": ["Lust", "Gluttony","Wrath"],
        "image":"don_quixote/n_corp_mittelhammer/n_corp_mittelhammer.png"
      },
      {
        "name": "[Lobotomy E.G.O::Lantern] Don Quixote",
        "rarity": 1,
        "damageTypes": ["Pierce", "Slash"],
        "sinTypes": ["Lust", "Gluttony","Gloom"],
        "image":"don_quixote/lobotomy_ego_lantern/lobotomy_ego_lantern.png"
      },
      {
        "name": "[Blade Lineage Salsu] Don Quixote",
        "rarity": 1,
        "damageTypes": ["Pierce", "Slash"],
        "sinTypes": ["Pride", "Envy","Sloth"],
        "image":"don_quixote/blade_lineage_salsu/blade_lineage_salsu.png"
      },
      {
        "name": "[W Crop. L3 Cleanup Agent] Don Quixote",
        "rarity": 2,
        "damageTypes": ["Slash", "Pierce"],
        "sinTypes": ["Sloth", "Gloom", "Envy"],
        "image":"don_quixote/w_corp_l3_cleanup_agent/w_corp_l3_cleanup_agent.png"
      },
      {
        "name": "[Cinq Assoc. South Section 5 Director] Don Quixote",
        "rarity": 2,
        "damageTypes": ["Pierce"],
        "sinTypes": ["Pride", "Gloom", "Lust"],
        "image":"don_quixote/cinq_assoc_south_section_5_director/cinq_assoc_south_section_5_director.png"
      },
      {
        "name": "[The Middle Little Sister] Don Quixote",
        "rarity": 2,
        "damageTypes": ["Blunt"],
        "sinTypes": ["Pride", "Envy", "Wrath"],
        "image":"don_quixote/the_middle_little_sister/the_middle_little_sister.png"
      },
      {
        "name": "[T Corp. Class 3 Collection Staff] Don Quixote",
        "rarity": 2,
        "damageTypes": ["Blunt", "Slash"],
        "sinTypes": ["Sloth", "Pride", "Gluttony"],
        "image":"don_quixote/t_corp_class_3_collection_staff/t_corp_class_3_collection_staff.png"
      },
      {
        "name": "[The Manager of La Manchaland] Don Quixote",
        "rarity": 2,
        "damageTypes": ["Pierce"],
        "sinTypes": ["Sloth", "Wrath", "Lust"],
        "image":"don_quixote/the_manager_of_la_manchaland/the_manager_of_la_manchaland.png"
      },
      {
        "name": "[Cinq Assoc. East Section 3] Don Quixote",
        "rarity": 2,
        "damageTypes": ["Pierce"],
        "sinTypes": ["Gluttony", "Wrath", "Pride"],
        "image":"don_quixote/cinq_assoc_east_section_3/cinq_assoc_east_section_3.png"
      },
      {
        "name": "[Lobotomy E.G.O::In the Name of Love and Hate] Don Quixote",
        "rarity": 2,
        "damageTypes": ["Blunt"],
        "sinTypes": ["Wrath", "Envy"],
        "image":"don_quixote/lobotomy_ego_in_the_name_of_love_and_hate/lobotomy_ego_in_the_name_of_love_and_hate.png"
      }
    ]
  },
  {
    "id": 3,
    "name": "Ryoshu",
    "icon": "Ryoshu_Icon.png",
    "identities": 
    [
      {
        "name": "[LCB Sinner] Ryoshu",
        "rarity": 0,
        "damageTypes": ["Slash"],
        "sinTypes": ["Gluttony", "Lust", "Pride"],
        "image":"ryoshu/lcb_sinner/lcb_sinner.png"
      },
      {
        "name": "[Seven Assoc. South Section 6] Ryoshu",
        "rarity": 1,
        "damageTypes": ["Blunt", "Slash"],
        "sinTypes": ["Gluttony", "Sloth", "Pride"],
        "image":"ryoshu/seven_assoc_south_section_6/seven_assoc_south_section_6.png"
      },
      {
        "name": "[LCCB Assistant Manager] Ryoshu",
        "rarity": 1,
        "damageTypes": ["Blunt", "Pierce"],
        "sinTypes": ["Gluttony", "Lust", "Pride"],
        "image":"ryoshu/lccb_assistant_manager/lccb_assistant_manager.png"
      },
      {
        "name": "[Liu Assoc. South Section 4] Ryoshu",
        "rarity": 1,
        "damageTypes": ["Slash", "Pierce"],
        "sinTypes": ["Gluttony", "Lust", "Wrath"],
        "image":"ryoshu/liu_assoc_south_section_4/liu_assoc_south_section_4.png"
      },
      {
        "name": "[District 20 Yurodivy] Ryoshu",
        "rarity": 1,
        "damageTypes": ["Blunt", "Pierce"],
        "sinTypes": ["Sloth", "Lust", "Gluttony"],
        "image":"ryoshu/district_20_yurodivy/district_20_yurodivy.png"
      },
      {
        "name": "[Kurokumo Clan Wakashu] Ryoshu",
        "rarity": 2,
        "damageTypes": ["Pierce"],
        "sinTypes": ["Pride", "Lust", "Gluttony"],
        "image":"ryoshu/kurokumo_clan_wakashu/kurokumo_clan_wakashu.png"
      },
      {
        "name": "[R.B. Chef de Cuisine] Ryoshu",
        "rarity": 2,
        "damageTypes": ["Slash", "Pierce"],
        "sinTypes": ["Wrath", "Envy", "Lust"],
        "image":"ryoshu/rb_chef_de_cuisine/rb_chef_de_cuisine.png"
      },
      {
        "name": "[W Corp. L3 Cleanup Agent] Ryoshu",
        "rarity": 2,
        "damageTypes": ["Slash"],
        "sinTypes": ["Lust", "Pride", "Envy"],
        "image":"ryoshu/w_corp_l3_cleanup_agent/w_corp_l3_cleanup_agent.png"
      },
      {
        "name": "[Edgar Family Chief Butler] Ryoshu",
        "rarity": 2,
        "damageTypes": ["Slash"],
        "sinTypes": ["Lust", "Pride", "Wrath"],
        "image":"ryoshu/edgar_family_chief_butler/edgar_family_chief_butler.png"
      },
      {
        "name": "[Lobotomy E.G.O::Red Eyes & Penitence] Ryoshu",
        "rarity": 2,
        "damageTypes": ["Blunt"],
        "sinTypes": ["Envy", "Gloom", "Lust"],
        "image":"ryoshu/lobotomy_ego_red_eyes_and_penitence/lobotomy_ego_red_eyes_and_penitence.png"
      },
      {
        "name": "[Heishou Pack - Mao Branch] Ryoshu",
        "rarity": 2,
        "damageTypes": ["Slash"],
        "sinTypes": ["Lust", "Gluttony", "Pride"],
        "image":"ryoshu/heishou_pack_mao_branch/heishou_pack_mao_branch.png"
      }
    ]
  },
  {
    "id": 4,
    "name": "Meursault",
    "icon": "Meursault_Icon.png",
    "identities": 
    [
      {
        "name": "[LCB Sinner] Meursault",
        "rarity": 0,
        "damageTypes": ["Blunt"],
        "sinTypes": ["Sloth", "Pride", "Gloom"],
        "image":"meursault/lcb_sinner/lcb_sinner.png"
      },
      {
        "name": "[Liu Assoc. South Section 6] Meursault",
        "rarity": 1,
        "damageTypes": ["Blunt", "Pierce"],
        "sinTypes": ["Lust", "Sloth", "Wrath"],
        "image":"meursault/liu_assoc_south_section_6/liu_assoc_south_section_6.png"
      },
      {
        "name": "[Rosespanner Workshop Fixer] Meursault",
        "rarity": 1,
        "damageTypes": ["Blunt"],
        "sinTypes": ["Gloom", "Pride", "Sloth"],
        "image":"meursault/rosespanner_workshop_fixer/rosespanner_workshop_fixer.png"
      },
      {
        "name": "[The Middle Little Brother] Meursault",
        "rarity": 1,
        "damageTypes": ["Blunt"],
        "sinTypes": ["Sloth", "Envy", "Wrath"],
        "image":"meursault/the_middle_little_brother/the_middle_little_brother.png"
      },
      {
        "name": "[Dead Rabbits Boss] Meursault",
        "rarity": 1,
        "damageTypes": ["Blunt", "Pierce"],
        "sinTypes": ["Lust", "Wrath", "Gluttony"],
        "image":"meursault/dead_rabbits_boss/dead_rabbits_boss.png"
      },
      {
        "name": "[W Corp. L2 Cleanup Agent] Meursault",
        "rarity": 2,
        "damageTypes": ["Slash"],
        "sinTypes": ["Envy", "Gloom", "Pride"],
        "image":"meursault/w_corp_cleanup_crew/w_corp_cleanup_crew.png"
      },
      {
        "name": "[N Corp. Großhammer] Meursault",
        "rarity": 2,
        "damageTypes": ["Blunt", "Pierce"],
        "sinTypes": ["Sloth", "Wrath", "Pride"],
        "image":"meursault/n_corp_grobhammer/n_corp_grobhammer.png"
      },
      {
        "name": "[R Corp. 4th Pack Rhino] Meursault",
        "rarity": 2,
        "damageTypes": ["Blunt", "Slash"],
        "sinTypes": ["Envy", "Gloom", "Lust"],
        "image":"meursault/r_corp_4th_pack_rhino/r_corp_4th_pack_rhino.png"
      },
      {
        "name": "[Blade Lineage Mentor] Meursault",
        "rarity": 2,
        "damageTypes": ["Slash"],
        "sinTypes": ["Pride", "Wrath", "Envy"],
        "image":"meursault/blade_lineage_mentor/blade_lineage_mentor.png"
      },
      {
        "name": "[Dieci Assoc. South Section 4 Director] Meursault",
        "rarity": 2,
        "damageTypes": ["Blunt", "Pierce"],
        "sinTypes": ["Gluttony", "Sloth", "Gloom"],
        "image":"meursault/dieci_assoc_south_section_4_director/dieci_assoc_south_section_4_director.png"
      },
      {
        "name": "[Cinq Assoc. West Section 3] Meursault",
        "rarity": 2,
        "damageTypes": ["Pierce"],
        "sinTypes": ["Pride", "Gluttony", "Gloom"],
        "image":"meursault/cinq_assoc_west_section_3/cinq_assoc_west_section_3.png"
      },
      {
        "name": "[The Thumb East Capo IIII Meursault] Meursault",
        "rarity": 2,
        "damageTypes": ["Slash", "Blunt"],
        "sinTypes": ["Sloth", "Wrath", "Lust"],
        "image":"meursault/the_thumb_east_capo_IIII/the_thumb_east_capo_IIII.png"
      }
    ]
  },
  {
    "id": 5,
    "name": "Hong Lu",
    "icon": "Hong_Lu_Icon.png",
    "identities": 
    [
      {
        "name": "[LCB Sinner] Hong Lu",
        "rarity": 0,
        "damageTypes": ["Blunt", "Slash"],
        "sinTypes": ["Pride", "Sloth", "Lust"],
        "image":"hong_lu/lcb_sinner/lcb_sinner.png"
      },
      {
        "name": "[Kurokumo Clan Wakashu] Hong Lu",
        "rarity": 1,
        "damageTypes": ["Slash"],
        "sinTypes": ["Lust", "Pride", "Sloth"],
        "image":"hong_lu/kurokumo_clan_wakashu/kurokumo_clan_wakashu.png"
      },
      {
        "name": "[Liu Assoc. South Section 5] Hong Lu",
        "rarity": 1,
        "damageTypes": ["Slash"],
        "sinTypes": ["Sloth", "Lust", "Wrath"],
        "image":"hong_lu/liu_assoc_south_section_5/liu_assoc_south_section_5.png"
      },
      {
        "name": "[Liu Assoc. South Section 5] Hong Lu",
        "rarity": 1,
        "damageTypes": ["Pierce", "Slash"],
        "sinTypes": ["Pride", "Wrath", "Gluttony"],
        "image":"hong_lu/w_corp_l2_cleanup_agent/w_corp_l2_cleanup_agent.png"
      },
      {
        "name": "[Hook Office Fixer] Hong Lu",
        "rarity": 1,
        "damageTypes": ["Pierce"],
        "sinTypes": ["Wrath", "Lust", "Pride"],
        "image":"hong_lu/hook_office_fixer/hook_office_fixer.png"
      },
      {
        "name": "[Fanghunt Office Fixer] Hong Lu",
        "rarity": 1,
        "damageTypes": ["Blunt"],
        "sinTypes": ["Gluttony", "Pride", "Wrath"],
        "image":"hong_lu/fanghunt_office_fixer/fanghunt_office_fixer.png"
      },
      {
        "name": "[Tingtang Gang Gangleader] Hong Lu",
        "rarity": 2,
        "damageTypes": ["Slash", "Pierce"],
        "sinTypes": ["Envy", "Lust", "Gluttony"],
        "image":"hong_lu/tingtang_gang_gangleader/tingtang_gang_gangleader.png"
      },
      {
        "name": "[K Corp. Class 3 Excision Staff] Hong Lu",
        "rarity": 2,
        "damageTypes": ["Slash", "Blunt"],
        "sinTypes": ["Pride", "Gluttony", "Sloth"],
        "image":"hong_lu/k_corp_class_3_excision_staff/k_corp_class_3_excision_staff.png"
      },
      {
        "name": "[Dieci Assoc. South Section 4] Hong Lu",
        "rarity": 2,
        "damageTypes": ["Slash", "Blunt"],
        "sinTypes": ["Wrath", "Gloom", "Sloth"],
        "image":"hong_lu/dieci_assoc_south_section_4/dieci_assoc_south_section_4.png"
      },
      {
        "name": "[District 20 Yurodivy] Hong Lu",
        "rarity": 2,
        "damageTypes": ["Pierce", "Blunt"],
        "sinTypes": ["Gloom", "Sloth", "Gluttony"],
        "image":"hong_lu/district_20_yurodivy/district_20_yurodivy.png"
      },
      {
        "name": "[Full-Stop Office Rep] Hong Lu",
        "rarity": 2,
        "damageTypes": ["Pierce", "Slash"],
        "sinTypes": ["Sloth", "Pride", "Gloom"],
        "image":"hong_lu/full_stop_office_rep/full_stop_office_rep.png"
      },
      {
        "name": "[R Corp. 4th Pack Reindeer] Hong Lu",
        "rarity": 2,
        "damageTypes": ["Blunt"],
        "sinTypes": ["Gluttony", "Envy", "Wrath"],
        "image":"hong_lu/r_corp_4th_pack_reindeer/r_corp_4th_pack_reindeer.png"
      },
      {
        "name": "[The Lord of Hongyuan] Hong Lu",
        "rarity": 2,
        "damageTypes": ["Slash"],
        "sinTypes": ["Gloom", "Gluttony", "Pride"],
        "image":"hong_lu/the_lord_of_hongyuan/the_lord_of_hongyuan.png"
      }
    ]
  },
  {
    "id": 6,
    "name": "Heathcliff",
    "icon": "Heathcliff_Icon.png",
    "identities": 
    [
      {
        "name": "[LCB Sinner] Heathcliff",
        "rarity": 0,
        "damageTypes": ["Blunt"],
        "sinTypes": ["Envy", "Wrath", "Lust"],
        "image":"heathcliff/lcb_sinner/lcb_sinner.png"
      },
      {
        "name": "[Shi Assoc. South Section 5] Heathcliff",
        "rarity": 1,
        "damageTypes": ["Slash", "Pierce"],
        "sinTypes": ["Lust", "Wrath", "Envy"],
        "image":"heathcliff/shi_assoc_south_section_5/shi_assoc_south_section_5.png"
      },
      {
        "name": "[N Corp. Kleinhammer] Heathcliff",
        "rarity": 1,
        "damageTypes": ["Blunt", "Pierce"],
        "sinTypes": ["Envy", "Gloom", "Lust"],
        "image":"heathcliff/n_corp_kleinhammer/n_corp_kleinhammer.png"
      },
      {
        "name": "[Seven Assoc. South Section 4] Heathcliff",
        "rarity": 1,
        "damageTypes": ["Slash", "Pierce"],
        "sinTypes": ["Wrath", "Envy", "Gluttony"],
        "image":"heathcliff/seven_assoc_south_section_4/seven_assoc_south_section_4.png"
      },
      {
        "name": "[MultiCrack Office Fixer] Heathcliff",
        "rarity": 1,
        "damageTypes": ["Slash", "Pierce"],
        "sinTypes": ["Wrath", "Envy", "Gloom"],
        "image":"heathcliff/multicrack_office_fixer/multicrack_office_fixer.png"
      },
      {
        "name": "[R Corp. 4th Pack Rabbit] Heathcliff",
        "rarity": 2,
        "damageTypes": ["Pierce"],
        "sinTypes": ["Wrath", "Gluttony", "Envy"],
        "image":"heathcliff/r_corp_4th_pack_rabbit/r_corp_4th_pack_rabbit.png"
      },
      {
        "name": "[Lobotomy E.G.O::Sunshower] Heathcliff",
        "rarity": 2,
        "damageTypes": ["Pierce", "Blunt"],
        "sinTypes": ["Envy", "Gloom", "Sloth"],
        "image":"heathcliff/lobotomy_ego_sunshower/lobotomy_ego_sunshower.png"
      },
      {
        "name": "[The Pequod Harpooneer] Heathcliff",
        "rarity": 2,
        "damageTypes": ["Pierce"],
        "sinTypes": ["Pride", "Envy", "Wrath"],
        "image":"heathcliff/the_pequod_harpooneer/the_pequod_harpooneer.png"
      },
      {
        "name": "[Öufi Assoc. South Section 3] Heathcliff",
        "rarity": 2,
        "damageTypes": ["Pierce", "Slash"],
        "sinTypes": ["Envy", "Gloom", "Pride"],
        "image":"heathcliff/oufi_assoc_south_section_3/oufi_assoc_south_section_3.png"
      },
      {
        "name": "[Wild Hunt] Heathcliff",
        "rarity": 2,
        "damageTypes": ["Blunt", "Slash"],
        "sinTypes": ["Wrath", "Envy", "Gloom", "Lust"],
        "image":"heathcliff/wild_hunt/wild_hunt.png"
      },
      {
        "name": "[Full-Stop Office Fixer] Heathcliff",
        "rarity": 2,
        "damageTypes": ["Pierce"],
        "sinTypes": ["Gloom", "Envy", "Pride"],
        "image":"heathcliff/full_stop_office_fixer/full_stop_office_fixer.png"
      },
      {
        "name": "[Kurokumo Clan Wakashu] Heathcliff",
        "rarity": 2,
        "damageTypes": ["Slash"],
        "sinTypes": ["Wrath", "Pride", "Lust"],
        "image":"heathcliff/kurokumo_clan_wakashu/kurokumo_clan_wakashu.png"
      }
    ]
  },
  {
    "id": 7,
    "name": "Ishmael",
    "icon": "Ishmael_Icon.png",
    "identities": 
    [
      {
        "name": "[LCB Sinner] Ishmael",
        "rarity": 0,
        "damageTypes": ["Blunt"],
        "sinTypes": ["Wrath", "Gluttony", "Gloom"],
        "image":"ishmael/lcb_sinner/lcb_sinner.png"
      },
      {
        "name": "[Shi Assoc. South Section 5] Ishmael",
        "rarity": 1,
        "damageTypes": ["Pierce", "Slash"],
        "sinTypes": ["Envy", "Lust", "Wrath"],
        "image":"ishmael/shi_assoc_south_section_5/shi_assoc_south_section_5.png"
      },
      {
        "name": "[LCCB Assistant Manager] Ishmael",
        "rarity": 1,
        "damageTypes": ["Blunt"],
        "sinTypes": ["Gluttony", "Gluttony", "Pride"],
        "image":"ishmael/lccb_assistant_manager/lccb_assistant_manager.png"
      },
      {
        "name": "[Lobotomy E.G.O::Sloshing] Ishmael",
        "rarity": 1,
        "damageTypes": ["Blunt"],
        "sinTypes": ["Gloom", "Wrath", "Gluttony"],
        "image":"ishmael/lobotomy_ego_sloshing/lobotomy_ego_sloshing.png"
      },
      {
        "name": "[Edgar Family Butler] Ishmael",
        "rarity": 1,
        "damageTypes": ["Blunt", "Slash"],
        "sinTypes": ["Sloth", "Gluttony", "Gloom"],
        "image":"ishmael/edgar_family_butler/edgar_family_butler.png"
      },
      {
        "name": "[R Corp. 4th Pack Reindeer] Ishmael",
        "rarity": 2,
        "damageTypes": ["Blunt"],
        "sinTypes": ["Gloom", "Envy", "Wrath"],
        "image":"ishmael/r_corp_4th_pack_reindeer/r_corp_4th_pack_reindeer.png"
      },
      {
        "name": "[Liu Assoc. South Section 4] Ishmael",
        "rarity": 2,
        "damageTypes": ["Blunt"],
        "sinTypes": ["Lust", "Wrath", "Envy"],
        "image":"ishmael/liu_assoc_south_section_4/liu_assoc_south_section_4.png"
      },
      {
        "name": "[Molar Boatworks Fixer] Ishmael",
        "rarity": 2,
        "damageTypes": ["Pierce"],
        "sinTypes": ["Pride", "Sloth", "Gloom"],
        "image":"ishmael/molar_boatworks_fixer/molar_boatworks_fixer.png"
      },
      {
        "name": "[The Pequod Captain] Ishmael",
        "rarity": 2,
        "damageTypes": ["Pierce"],
        "sinTypes": ["Envy", "Pride", "Wrath"],
        "image":"ishmael/the_pequod_captain/the_pequod_captain.png"
      },
      {
        "name": "[Zwei Assoc. West Section 3] Ishmael",
        "rarity": 2,
        "damageTypes": ["Blunt"],
        "sinTypes": ["Pride", "Envy", "Gluttony"],
        "image":"ishmael/zwei_assoc_west_section_3/zwei_assoc_west_section_3.png"
      },
      {
        "name": "[Kurokumo Clan Captain] Ishmael",
        "rarity": 2,
        "damageTypes": ["Slash"],
        "sinTypes": ["Envy", "Pride", "Lust"],
        "image":"ishmael/kurokumo_clan_captain/kurokumo_clan_captain.png"
      },
      {
        "name": "[Family Hierarch Candidate] Ishmael",
        "rarity": 2,
        "damageTypes": ["Slash", "Blunt"],
        "sinTypes": ["Gloom", "Gluttony", "Envy"],
        "image":"ishmael/family_hierarch_candidate/family_hierarch_candidate.png"
      }
    ]
  },
  {
    "id": 8,
    "name": "Rodion",
    "icon": "Rodion_Icon.png",
    "identities": 
    [
      {
        "name": "[LCB Sinner] Rodion",
        "rarity": 0,
        "damageTypes": ["Slash"],
        "sinTypes": ["Gluttony", "Pride", "Wrath"],
        "image":"rodion/lcb_sinner/lcb_sinner.png"
      },
      {
        "name": "[LCCB Assistant Manager] Rodion",
        "rarity": 1,
        "damageTypes": ["Blunt"],
        "sinTypes": ["Pride", "Gluttony", "Envy"],
        "image":"rodion/lccb_assistant_manager/lccb_assistant_manager.png"
      },
      {
        "name": "[N Corp. Mittelhammer] Rodion",
        "rarity": 1,
        "damageTypes": ["Pierce", "Blunt"],
        "sinTypes": ["Pride", "Lust", "Wrath"],
        "image":"rodion/n_corp_mittelhammer/n_corp_mittelhammer.png"
      },
      {
        "name": "[Zwei Assoc. South Section 5] Rodion",
        "rarity": 1,
        "damageTypes": ["Blunt"],
        "sinTypes": ["Wrath", "Sloth", "Gloom"],
        "image":"rodion/zwei_assoc_south_section_5/zwei_assoc_south_section_5.png"
      },
      {
        "name": "[T Corp. Class 2 Collection Staff] Rodion",
        "rarity": 1,
        "damageTypes": ["Blunt"],
        "sinTypes": ["Envy", "Wrath", "Sloth"],
        "image":"rodion/t_corp_class_2_collection_staff/t_corp_class_2_collection_staff.png"
      },
      {
        "name": "[Kurokumo Clan Wakashu] Rodion",
        "rarity": 2,
        "damageTypes": ["Slash"],
        "sinTypes": ["Gloom", "Lust", "Pride"],
        "image":"rodion/kurokumo_clan_wakashu/kurokumo_clan_wakashu.png"
      },
      {
        "name": "[Rosespanner Workshop Rep] Rodion",
        "rarity": 2,
        "damageTypes": ["Blunt", "Pierce"],
        "sinTypes": ["Pride", "Gloom", "Envy"],
        "image":"rodion/rosespanner_workshop_rep/rosespanner_workshop_rep.png"
      },
      {
        "name": "[Dieci Assoc. South Section 4] Rodion",
        "rarity": 2,
        "damageTypes": ["Blunt"],
        "sinTypes": ["Gloom", "Envy", "Sloth"],
        "image":"rodion/dieci_assoc_south_section_4/dieci_assoc_south_section_4.png"
      },
      {
        "name": "[Liu Assoc. South Section 4 Director] Rodion",
        "rarity": 2,
        "damageTypes": ["Blunt", "Pierce"],
        "sinTypes": ["Pride", "Wrath", "Lust"],
        "image":"rodion/liu_assoc_south_section_4_director/liu_assoc_south_section_4_director.png"
      },
      {
        "name": "[Devyat' Assoc. North Section 3] Rodion",
        "rarity": 2,
        "damageTypes": ["Slash"],
        "sinTypes": ["Lust", "Wrath", "Gluttony"],
        "image":"rodion/devyat_assoc_north_section_3/devyat_assoc_north_section_3.png"
      },
      {
        "name": "[The Princess of La Manchaland] Rodion",
        "rarity": 2,
        "damageTypes": ["Pierce"],
        "sinTypes": ["Pride", "Envy", "Lust"],
        "image":"rodion/the_princess_of_lamanchaland/the_princess_of_lamanchaland.png"
      },
      {
        "name": "[Heishou Pack - Si Branch] Rodion",
        "rarity": 2,
        "damageTypes": ["Pierce", "Slash"],
        "sinTypes": ["Envy", "Gluttony", "Gloom"],
        "image":"rodion/heishou_pack_si_branch/heishou_pack_si_branch.png"
      },
      {
        "name": "[Lobotomy E.G.O::The Sword Sharpened with Tears] Rodion",
        "rarity": 2,
        "damageTypes": ["Pierce", "Slash"],
        "sinTypes": ["Gloom", "Envy", "Pride"],
        "image":"rodion/lobotomy_ego_the_sword_sharpened_with_tears/lobotomy_ego_the_sword_sharpened_with_tears.png"
      }
    ]
  },
  {
    "id": 9,
    "name": "Sinclair",
    "icon": "Sinclair_Icon.png",
    "identities": 
    [
      {
        "name": "[LCB Sinner] Sinclair",
        "rarity": 0,
        "damageTypes": ["Slash"],
        "sinTypes": ["Pride", "Wrath", "Envy"],
        "image":"sinclair/lcb_sinner/lcb_sinner.png"
      },
      {
        "name": "[Zwei Assoc. South Section 6] Sinclair",
        "rarity": 1,
        "damageTypes": ["Blunt"],
        "sinTypes": ["Gloom", "Wrath", "Sloth"],
        "image":"sinclair/zwei_assoc_south_section_6/zwei_assoc_south_section_6.png"
      },
      {
        "name": "[Los Mariachis Jefe] Sinclair",
        "rarity": 1,
        "damageTypes": ["Blunt"],
        "sinTypes": ["Sloth", "Envy", "Gloom"],
        "image":"sinclair/los_mariachis_jefe/los_mariachis_jefe.png"
      },
      {
        "name": "[Lobotomy E.G.O::Red Sheet] Sinclair",
        "rarity": 1,
        "damageTypes": ["Blunt", "Pierce"],
        "sinTypes": ["Gluttony", "Pride", "Lust"],
        "image":"sinclair/lobotomy_ego_red_sheet/lobotomy_ego_red_sheet.png"
      },
      {
        "name": "[Molar Boatworks Fixer] Sinclair",
        "rarity": 1,
        "damageTypes": ["Blunt", "Pierce"],
        "sinTypes": ["Gloom", "Envy", "Gluttony"],
        "image":"sinclair/molar_boatworks_fixer/molar_boatworks_fixer.png"
      },
      {
        "name": "[Zwei Assoc. West Section 3] Sinclair",
        "rarity": 1,
        "damageTypes": ["Blunt", "Slash"],
        "sinTypes": ["Lust", "Gloom", "Sloth"],
        "image":"sinclair/zwei_assoc_west_section_3/zwei_assoc_west_section_3.png"
      },
      {
        "name": "[Blade Lineage Salsu] Sinclair",
        "rarity": 2,
        "damageTypes": ["Pierce", "Slash"],
        "sinTypes": ["Gluttony", "Wrath", "Pride"],
        "image":"sinclair/blade_lineage_salsu/blade_lineage_salsu.png"
      },
      {
        "name": "[The One Who Shall Grip] Sinclair",
        "rarity": 2,
        "damageTypes": ["Pierce", "Slash"],
        "sinTypes": ["Gluttony", "Lust", "Wrath"],
        "image":"sinclair/the_one_who_shall_grip/the_one_who_shall_grip.png"
      },
      {
        "name": "[Cinq Assoc. South Section 4 Director] Sinclair",
        "rarity": 2,
        "damageTypes": ["Pierce", "Slash"],
        "sinTypes": ["Gluttony", "Pride", "Lust"],
        "image":"sinclair/cinq_assoc_south_section_4_director/cinq_assoc_south_section_4_director.png"
      },
      {
        "name": "[Dawn Office Fixer] Sinclair",
        "rarity": 2,
        "damageTypes": ["Pierce", "Slash"],
        "sinTypes": ["Gloom", "Envy", "Wrath"],
        "image":"sinclair/dawn_office_fixer/dawn_office_fixer.png"
      },
      {
        "name": "[Devyat' Assoc. North Section 3] Sinclair",
        "rarity": 2,
        "damageTypes": ["Blunt"],
        "sinTypes": ["Lust", "Gloom", "Wrath"],
        "image":"sinclair/devyat_assoc_north_section_3/devyat_assoc_north_section_3.png"
      },
      {
        "name": "[The Middle Little Brother] Sinclair",
        "rarity": 2,
        "damageTypes": ["Blunt"],
        "sinTypes": ["Gloom", "Envy"],
        "image":"sinclair/the_middle_little_brother/the_middle_little_brother.png"
      },
      {
        "name": "[The Thumb East Soldato II] Sinclair",
        "rarity": 2,
        "damageTypes": ["Blunt"],
        "sinTypes": ["Lust", "Sloth", "Wrath"],
        "image":"sinclair/the_thumb_east_soldato_II/the_thumb_east_soldato_II.png"
      }
    ]
  },
  {
    "id": 10,
    "name": "Outis",
    "icon": "Outis_Icon.png",
    "identities": 
    [
      {
        "name": "[LCB Sinner] Outis",
        "rarity": 0,
        "damageTypes": ["Pierce", "Slash"],
        "sinTypes": ["Sloth", "Pride", "Gloom"],
        "image":"outis/lcb_sinner/lcb_sinner.png"
      },
      {
        "name": "[Blade Lineage Salsu] Outis",
        "rarity": 1,
        "damageTypes": ["Pierce", "Slash"],
        "sinTypes": ["Wrath", "Lust", "Pride"],
        "image":"outis/blade_lineage_salsu/blade_lineage_salsu.png"
      },
      {
        "name": "[Cinq Assoc. South Section 4] Outis",
        "rarity": 1,
        "damageTypes": ["Pierce"],
        "sinTypes": ["Pride", "Gloom", "Lust"],
        "image":"outis/cinq_assoc_south_section_4/cinq_assoc_south_section_4.png"
      },
      {
        "name": "[The Ring Pointillist Student] Outis",
        "rarity": 1,
        "damageTypes": ["Pierce"],
        "sinTypes": ["Lust", "Wrath", "Gluttony"],
        "image":"outis/the_ring_pointillist_student/the_ring_pointillist_student.png"
      },
      {
        "name": "[Seven Assoc. South Section 6] Outis",
        "rarity": 2,
        "damageTypes": ["Blunt", "Slash"],
        "sinTypes": ["Gloom", "Sloth", "Lust"],
        "image":"outis/seven_assoc_south_section_6_director/seven_assoc_south_section_6_director.png"
      },
      {
        "name": "[Molar Office Fixer] Outis",
        "rarity": 2,
        "damageTypes": ["Blunt", "Slash"],
        "sinTypes": ["Wrath", "Lust", "Sloth"],
        "image":"outis/molar_office_fixer/molar_office_fixer.png"
      },
      {
        "name": "[Lobotomy E.G.O::Magic Bullet] Outis",
        "rarity": 2,
        "damageTypes": ["Blunt", "Pierce"],
        "sinTypes": ["Wrath", "Pride"],
        "image":"outis/lobotomy_ego_magic_bullet/lobotomy_ego_magic_bullet.png"
      },
      {
        "name": "[Wuthering Heights Chief Butler] Outis",
        "rarity": 2,
        "damageTypes": ["Blunt"],
        "sinTypes": ["Pride", "Gloom", "Lust"],
        "image":"outis/wuthering_heights_chief_butler/wuthering_heights_chief_butler.png"
      },
      {
        "name": "[W Corp. L3 Cleanup Captain] Outis",
        "rarity": 2,
        "damageTypes": ["Blunt", "Slash"],
        "sinTypes": ["Pride", "Envy", "Gloom"],
        "image":"outis/w_corp_l3_cleanup_captain/w_corp_l3_cleanup_captain.png"
      },
      {
        "name": "[The Barber of La Manchaland] Outis",
        "rarity": 2,
        "damageTypes": ["Blunt", "Slash"],
        "sinTypes": ["Gluttony", "Lust", "Wrath"],
        "image":"outis/the_barber_of_la_manchaland/the_barber_of_la_manchaland.png"
      },
      {
        "name": "[Heishou Pack - Mao Branch] Outis",
        "rarity": 2,
        "damageTypes": ["Slash"],
        "sinTypes": ["Sloth", "Gluttony", "Gloom"],
        "image":"outis/heishou_pack_mao_branch/heishou_pack_mao_branch.png"
      },
      {
        "name": "[T Corp. Class 3 VDCU Staff ] Outis",
        "rarity": 2,
        "damageTypes": ["Blunt"],
        "sinTypes": ["Pride", "Sloth", "Lust"],
        "image":"outis/t_corp_class_3_vdcu_staff/t_corp_class_3_vdcu_staff.png"
      }
    ]
  },
  {
    "id": 11,
    "name": "Gregor",
    "icon": "Gregor_Icon.png",
    "identities": 
    [
      {
        "name": "[LCB Sinner] Gregor",
        "rarity": 0,
        "damageTypes": ["Slash", "Pierce"],
        "sinTypes": ["Gloom", "Gluttony", "Sloth"],
        "image":"gregor/lcb_sinner/lcb_sinner.png"
      },
      {
        "name": "[Liu Assoc. South Section 6] Gregor",
        "rarity": 1,
        "damageTypes": ["Blunt"],
        "sinTypes": ["Wrath", "Lust", "Sloth"],
        "image":"gregor/liu_assoc_south_section_6/liu_assoc_south_section_6.png"
      },
      {
        "name": "[R.B. Sous-chef] Gregor",
        "rarity": 1,
        "damageTypes": ["Blunt", "Slash"],
        "sinTypes": ["Lust", "Gluttony", "Envy"],
        "image":"gregor/rb_sous_chef/rb_sous_chef.png"
      },
      {
        "name": "[Rosespanner Workshop Fixer] Gregor",
        "rarity": 1,
        "damageTypes": ["Pierce", "Slash"],
        "sinTypes": ["Gluttony", "Envy", "Gloom"],
        "image":"gregor/rosespanner_workshop_fixer/rosespanner_workshop_fixer.png"
      },
      {
        "name": "[Kurokumo Clan Captain] Gregor",
        "rarity": 1,
        "damageTypes": ["Blunt", "Slash"],
        "sinTypes": ["Sloth", "Lust", "Gloom"],
        "image":"gregor/kurokumo_clan_captain/kurokumo_clan_captain.png"
      },
      {
        "name": "[G Corp. Manager Corporal] Gregor",
        "rarity": 2,
        "damageTypes": ["Pierce", "Slash"],
        "sinTypes": ["Gluttony", "Sloth", "Lust"],
        "image":"gregor/g_corp_corporal_manager/g_corp_corporal_manager.png"
      },
      {
        "name": "[Zwei Assoc. South Section 4] Gregor",
        "rarity": 2,
        "damageTypes": ["Slash"],
        "sinTypes": ["Sloth", "Gluttony", "Gloom"],
        "image":"gregor/zwei_assoc_south_section_4/zwei_assoc_south_section_4.png"
      },
      {
        "name": "[Twinhook Pirates First Mate] Gregor",
        "rarity": 2,
        "damageTypes": ["Pierce"],
        "sinTypes": ["Sloth", "Pride", "Gloom"],
        "image":"gregor/twinhook_pirates_first_mate/twinhook_pirates_first_mate.png"
      },
      {
        "name": "[Edgar Family Heir] Gregor",
        "rarity": 2,
        "damageTypes": ["Slash"],
        "sinTypes": ["Envy", "Gloom", "Lust"],
        "image":"gregor/edgar_family_heir/edgar_family_heir.png"
      },
      {
        "name": "[The Priest of La Manchaland] Gregor",
        "rarity": 2,
        "damageTypes": ["Blunt"],
        "sinTypes": ["Gluttony", "Pride", "Lust"],
        "image":"gregor/the_priest_of_la_manchaland/the_priest_of_la_manchaland.png"
      },
      {
        "name": "[Firefist Office Survivor] Gregor",
        "rarity": 2,
        "damageTypes": ["Blunt"],
        "sinTypes": ["Lust", "Wrath", "Gloom"],
        "image":"gregor/firefist_office_survivor/firefist_office_survivor.png"
      },
      {
        "name": "[Heishou Pack - Si Branch] Gregor",
        "rarity": 2,
        "damageTypes": ["Pierce", "Slash"],
        "sinTypes": ["Pride", "Gluttony", "Envy"],
        "image":"gregor/heishou_pack_si_branch/heishou_pack_si_branch.png"
      }
    ]
  }
]